random_number_ltds/__init__.py
random_number_ltds/random_number_generator.py
random_number_ltds-0.0.1.dist-info/LICENSE
random_number_ltds-0.0.1.dist-info/METADATA
random_number_ltds-0.0.1.dist-info/WHEEL
random_number_ltds-0.0.1.dist-info/top_level.txt
random_number_ltds-0.0.1.dist-info/RECORD
